Workbook

Sheet Cover
B2: SAAS FINANCIAL MODEL - INSTITUTIONAL GRADE
B4: Proprietary & Confidential - Prepared for Review
B6: DATE: | C6: March 26, 2026
B7: VERSION: | C7: 1.0 - Goldman Sachs Associate Build
B9: TABLE OF CONTENTS
B11: Dashboard | C11: Executive KPIs & Performance Metrics
B12: Assumptions_SNA | C12: Scenario Toggle & Global Inputs
B13: Revenue_Build | C13: Bottom-up Sales Funnel & MRR Build
B14: Operating_Expenses | C14: Departmental OPEX & Headcount
B15: Financials | C15: 3-Statement Integrated Financials
B16: SNA_Outputs | C16: Scenario & Sensitivity Tables

Sheet Assumptions_SNA
B2: SCENARIO TOGGLE
B4: Active Scenario (1=Base, 2=Bull, 3=Bear) | C4: 1
B6: GLOBAL ASSUMPTIONS
B7: Model Start Date | C7: 46023
B9: OPERATIONAL DRIVERS BY SCENARIO
C10: Base | D10: Bull | E10: Bear
B11: Lead Growth Rate (MoM %) | C11: 0.05 | D11: 0.08 | E11: 0.02
B12: Churn Rate (MoM %) | C12: 0.02 | D12: 0.01 | E12: 0.04
B13: Expansion Rate (MoM %) | C13: 0.01 | D13: 0.03 | E13: 0.005
B14: Avg Revenue Per User (ARPU) | C14: 1500 | D14: 2000 | E14: 1000
B15: Sales Commission (%) | C15: 0.1 | D15: 0.1 | E15: 0.1
B16: Server Cost per User | C16: 50 | D16: 40 | E16: 60
B20: ACTIVE DRIVER SELECTION
B21: Lead Growth Rate (MoM %) | C21: =INDEX($C$11:$E$11, $C$4)
B22: Churn Rate (MoM %) | C22: =INDEX($C$12:$E$12, $C$4)
B23: Expansion Rate (MoM %) | C23: =INDEX($C$13:$E$13, $C$4)
B24: Avg Revenue Per User (ARPU) | C24: =INDEX($C$14:$E$14, $C$4)
B25: Sales Commission (%) | C25: =INDEX($C$15:$E$15, $C$4)
B26: Server Cost per User | C26: =INDEX($C$16:$E$16, $C$4)

Sheet Revenue_Build
B2: REVENUE BUILD - MONTHLY PERFORMANCE
C3: =EDATE(Assumptions_SNA!$C$7, 0) | D3: =EDATE(Assumptions_SNA!$C$7, 1) | E3: =EDATE(Assumptions_SNA!$C$7, 2) | F3: =EDATE(Assumptions_SNA!$C$7, 3) | G3: =EDATE(Assumptions_SNA!$C$7, 4) | H3: =EDATE(Assumptions_SNA!$C$7, 5) | I3: =EDATE(Assumptions_SNA!$C$7, 6) | J3: =EDATE(Assumptions_SNA!$C$7, 7) | K3: =EDATE(Assumptions_SNA!$C$7, 8) | L3: =EDATE(Assumptions_SNA!$C$7, 9) | M3: =EDATE(Assumptions_SNA!$C$7, 10) | N3: =EDATE(Assumptions_SNA!$C$7, 11) | O3: =EDATE(Assumptions_SNA!$C$7, 12) | P3: =EDATE(Assumptions_SNA!$C$7, 13) | Q3: =EDATE(Assumptions_SNA!$C$7, 14) | R3: =EDATE(Assumptions_SNA!$C$7, 15) | S3: =EDATE(Assumptions_SNA!$C$7, 16) | T3: =EDATE(Assumptions_SNA!$C$7, 17) | U3: =EDATE(Assumptions_SNA!$C$7, 18) | V3: =EDATE(Assumptions_SNA!$C$7, 19) | W3: =EDATE(Assumptions_SNA!$C$7, 20) | X3: =EDATE(Assumptions_SNA!$C$7, 21) | Y3: =EDATE(Assumptions_SNA!$C$7, 22) | Z3: =EDATE(Assumptions_SNA!$C$7, 23) | AA3: =EDATE(Assumptions_SNA!$C$7, 24) | AB3: =EDATE(Assumptions_SNA!$C$7, 25) | AC3: =EDATE(Assumptions_SNA!$C$7, 26) | AD3: =EDATE(Assumptions_SNA!$C$7, 27) | AE3: =EDATE(Assumptions_SNA!$C$7, 28) | AF3: =EDATE(Assumptions_SNA!$C$7, 29) | AG3: =EDATE(Assumptions_SNA!$C$7, 30) | AH3: =EDATE(Assumptions_SNA!$C$7, 31) | AI3: =EDATE(Assumptions_SNA!$C$7, 32) | AJ3: =EDATE(Assumptions_SNA!$C$7, 33) | AK3: =EDATE(Assumptions_SNA!$C$7, 34) | AL3: =EDATE(Assumptions_SNA!$C$7, 35) | AM3: =EDATE(Assumptions_SNA!$C$7, 36) | AN3: =EDATE(Assumptions_SNA!$C$7, 37) | AO3: =EDATE(Assumptions_SNA!$C$7, 38) | AP3: =EDATE(Assumptions_SNA!$C$7, 39) | AQ3: =EDATE(Assumptions_SNA!$C$7, 40) | AR3: =EDATE(Assumptions_SNA!$C$7, 41) | AS3: =EDATE(Assumptions_SNA!$C$7, 42) | AT3: =EDATE(Assumptions_SNA!$C$7, 43) | AU3: =EDATE(Assumptions_SNA!$C$7, 44) | AV3: =EDATE(Assumptions_SNA!$C$7, 45) | AW3: =EDATE(Assumptions_SNA!$C$7, 46) | AX3: =EDATE(Assumptions_SNA!$C$7, 47) | AY3: =EDATE(Assumptions_SNA!$C$7, 48) | AZ3: =EDATE(Assumptions_SNA!$C$7, 49) | BA3: =EDATE(Assumptions_SNA!$C$7, 50) | BB3: =EDATE(Assumptions_SNA!$C$7, 51) | BC3: =EDATE(Assumptions_SNA!$C$7, 52) | BD3: =EDATE(Assumptions_SNA!$C$7, 53) | BE3: =EDATE(Assumptions_SNA!$C$7, 54) | BF3: =EDATE(Assumptions_SNA!$C$7, 55) | BG3: =EDATE(Assumptions_SNA!$C$7, 56) | BH3: =EDATE(Assumptions_SNA!$C$7, 57) | BI3: =EDATE(Assumptions_SNA!$C$7, 58) | BJ3: =EDATE(Assumptions_SNA!$C$7, 59)
B5: SALES FUNNEL
B6: Target Leads | C6: 5000 | D6: =C6*(1+Assumptions_SNA!$C$21) | E6: =D6*(1+Assumptions_SNA!$C$21) | F6: =E6*(1+Assumptions_SNA!$C$21) | G6: =F6*(1+Assumptions_SNA!$C$21) | H6: =G6*(1+Assumptions_SNA!$C$21) | I6: =H6*(1+Assumptions_SNA!$C$21) | J6: =I6*(1+Assumptions_SNA!$C$21) | K6: =J6*(1+Assumptions_SNA!$C$21) | ... BJ6: =BI6*(1+Assumptions_SNA!$C$21)
B7: Conversion Rate | C7: 0.02 | D7: 0.02 | E7: 0.02 | F7: 0.02 | G7: 0.02 | H7: 0.02 | I7: 0.02 | J7: 0.02 | K7: 0.02 | L7: 0.02 | M7: 0.02 | N7: 0.02 | O7: 0.02 | P7: 0.02 | Q7: 0.02 | R7: 0.02 | S7: 0.02 | T7: 0.02 | U7: 0.02 | V7: 0.02 | W7: 0.02 | X7: 0.02 | Y7: 0.02 | Z7: 0.02 | AA7: 0.02 | AB7: 0.02 | AC7: 0.02 | AD7: 0.02 | AE7: 0.02 | AF7: 0.02 | AG7: 0.02 | AH7: 0.02 | AI7: 0.02 | AJ7: 0.02 | AK7: 0.02 | AL7: 0.02 | AM7: 0.02 | AN7: 0.02 | AO7: 0.02 | AP7: 0.02 | AQ7: 0.02 | AR7: 0.02 | AS7: 0.02 | AT7: 0.02 | AU7: 0.02 | AV7: 0.02 | AW7: 0.02 | AX7: 0.02 | AY7: 0.02 | AZ7: 0.02 | BA7: 0.02 | BB7: 0.02 | BC7: 0.02 | BD7: 0.02 | BE7: 0.02 | BF7: 0.02 | BG7: 0.02 | BH7: 0.02 | BI7: 0.02 | BJ7: 0.02
B8: New Customers Acquired | C8: =C6*C7 | D8: =D6*D7 | E8: =E6*E7 | F8: =F6*F7 | G8: =G6*G7 | H8: =H6*H7 | I8: =I6*I7 | J8: =J6*J7 | ... BJ8: =BJ6*BJ7
B10: MRR WATERFALL
B11: Beginning MRR | C11: 0 | D11: =C16 | E11: =D16 | F11: =E16 | G11: =F16 | H11: =G16 | I11: =H16 | J11: =I16 | K11: =J16 | ... BJ11: =BI16
B12: New MRR | C12: =C8*Assumptions_SNA!$C$24 | D12: =D8*Assumptions_SNA!$C$24 | E12: =E8*Assumptions_SNA!$C$24 | F12: =F8*Assumptions_SNA!$C$24 | G12: =G8*Assumptions_SNA!$C$24 | H12: =H8*Assumptions_SNA!$C$24 | I12: =I8*Assumptions_SNA!$C$24 | J12: =J8*Assumptions_SNA!$C$24 | ... BJ12: =BJ8*Assumptions_SNA!$C$24
B13: Expansion MRR | C13: =C11*Assumptions_SNA!$C$23 | D13: =D11*Assumptions_SNA!$C$23 | E13: =E11*Assumptions_SNA!$C$23 | F13: =F11*Assumptions_SNA!$C$23 | G13: =G11*Assumptions_SNA!$C$23 | H13: =H11*Assumptions_SNA!$C$23 | I13: =I11*Assumptions_SNA!$C$23 | J13: =J11*Assumptions_SNA!$C$23 | ... BJ13: =BJ11*Assumptions_SNA!$C$23
B14: Churn MRR | C14: =-C11*Assumptions_SNA!$C$22 | D14: =-D11*Assumptions_SNA!$C$22 | E14: =-E11*Assumptions_SNA!$C$22 | F14: =-F11*Assumptions_SNA!$C$22 | G14: =-G11*Assumptions_SNA!$C$22 | H14: =-H11*Assumptions_SNA!$C$22 | I14: =-I11*Assumptions_SNA!$C$22 | J14: =-J11*Assumptions_SNA!$C$22 | ... BJ14: =-BJ11*Assumptions_SNA!$C$22
B15: Net MRR Movement | C15: =SUM(C12:C14) | D15: =SUM(D12:D14) | E15: =SUM(E12:E14) | F15: =SUM(F12:F14) | G15: =SUM(G12:G14) | H15: =SUM(H12:H14) | I15: =SUM(I12:I14) | J15: =SUM(J12:J14) | ... BJ15: =SUM(BJ12:BJ14)
B16: Ending MRR | C16: =C11+C15 | D16: =D11+D15 | E16: =E11+E15 | F16: =F11+F15 | G16: =G11+G15 | H16: =H11+H15 | I16: =I11+I15 | J16: =J11+J15 | ... BJ16: =BJ11+BJ15

Sheet Financials
B2: CONSOLIDATED INCOME STATEMENT
C3: ='Revenue_Build'!C3 | D3: ='Revenue_Build'!D3 | E3: ='Revenue_Build'!E3 | F3: ='Revenue_Build'!F3 | G3: ='Revenue_Build'!G3 | H3: ='Revenue_Build'!H3 | I3: ='Revenue_Build'!I3 | J3: ='Revenue_Build'!J3 | ... BJ3: ='Revenue_Build'!BJ3
B5: REVENUE | C5: ='Revenue_Build'!C15 | D5: ='Revenue_Build'!D15 | E5: ='Revenue_Build'!E15 | F5: ='Revenue_Build'!F15 | G5: ='Revenue_Build'!G15 | H5: ='Revenue_Build'!H15 | I5: ='Revenue_Build'!I15 | J5: ='Revenue_Build'!J15 | ... BJ5: ='Revenue_Build'!BJ15
B6: Cost of Goods Sold | C6: =('Revenue_Build'!C15/Assumptions_SNA!$C$24)*Assumptions_SNA!$C$26 | D6: =('Revenue_Build'!D15/Assumptions_SNA!$C$24)*Assumptions_SNA!$C$26 | E6: =('Revenue_Build'!E15/Assumptions_SNA!$C$24)*Assumptions_SNA!$C$26 | F6: =('Revenue_Build'!F15/Assumptions_SNA!$C$24)*Assumptions_SNA!$C$26 | G6: =('Revenue_Build'!G15/Assumptions_SNA!$C$24)*Assumptions_SNA!$C$26 | H6: =('Revenue_Build'!H15/Assumptions_SNA!$C$24)*Assumptions_SNA!$C$26 | I6: =('Revenue_Build'!I15/Assumptions_SNA!$C$24)*Assumptions_SNA!$C$26 | J6: =('Revenue_Build'!J15/Assumptions_SNA!$C$24)*Assumptions_SNA!$C$26 | ... BJ6: =('Revenue_Build'!BJ15/Assumptions_SNA!$C$24)*Assumptions_SNA!$C$26
B7: GROSS PROFIT | C7: =C5-C6 | D7: =D5-D6 | E7: =E5-E6 | F7: =F5-F6 | G7: =G5-G6 | H7: =H5-H6 | I7: =I5-I6 | J7: =J5-J6 | ... BJ7: =BJ5-BJ6
B8: Operating Expenses
B9: Sales & Marketing | C9: =C5*Assumptions_SNA!$C$25 + 10000 | D9: =D5*Assumptions_SNA!$C$25 + 10000 | E9: =E5*Assumptions_SNA!$C$25 + 10000 | F9: =F5*Assumptions_SNA!$C$25 + 10000 | G9: =G5*Assumptions_SNA!$C$25 + 10000 | H9: =H5*Assumptions_SNA!$C$25 + 10000 | I9: =I5*Assumptions_SNA!$C$25 + 10000 | J9: =J5*Assumptions_SNA!$C$25 + 10000 | ... BJ9: =BJ5*Assumptions_SNA!$C$25 + 10000
B10: Research & Development | C10: 25000 | D10: 25000 | E10: 25000 | F10: 25000 | G10: 25000 | H10: 25000 | I10: 25000 | J10: 25000 | K10: 25000 | L10: 25000 | M10: 25000 | N10: 25000 | O10: 25000 | P10: 25000 | Q10: 25000 | R10: 25000 | S10: 25000 | T10: 25000 | U10: 25000 | V10: 25000 | W10: 25000 | X10: 25000 | Y10: 25000 | Z10: 25000 | AA10: 25000 | AB10: 25000 | AC10: 25000 | AD10: 25000 | AE10: 25000 | AF10: 25000 | AG10: 25000 | AH10: 25000 | AI10: 25000 | AJ10: 25000 | AK10: 25000 | AL10: 25000 | AM10: 25000 | AN10: 25000 | AO10: 25000 | AP10: 25000 | AQ10: 25000 | AR10: 25000 | AS10: 25000 | AT10: 25000 | AU10: 25000 | AV10: 25000 | AW10: 25000 | AX10: 25000 | AY10: 25000 | AZ10: 25000 | BA10: 25000 | BB10: 25000 | BC10: 25000 | BD10: 25000 | BE10: 25000 | BF10: 25000 | BG10: 25000 | BH10: 25000 | BI10: 25000 | BJ10: 25000
B11: General & Admin | C11: 15000 | D11: 15000 | E11: 15000 | F11: 15000 | G11: 15000 | H11: 15000 | I11: 15000 | J11: 15000 | K11: 15000 | L11: 15000 | M11: 15000 | N11: 15000 | O11: 15000 | P11: 15000 | Q11: 15000 | R11: 15000 | S11: 15000 | T11: 15000 | U11: 15000 | V11: 15000 | W11: 15000 | X11: 15000 | Y11: 15000 | Z11: 15000 | AA11: 15000 | AB11: 15000 | AC11: 15000 | AD11: 15000 | AE11: 15000 | AF11: 15000 | AG11: 15000 | AH11: 15000 | AI11: 15000 | AJ11: 15000 | AK11: 15000 | AL11: 15000 | AM11: 15000 | AN11: 15000 | AO11: 15000 | AP11: 15000 | AQ11: 15000 | AR11: 15000 | AS11: 15000 | AT11: 15000 | AU11: 15000 | AV11: 15000 | AW11: 15000 | AX11: 15000 | AY11: 15000 | AZ11: 15000 | BA11: 15000 | BB11: 15000 | BC11: 15000 | BD11: 15000 | BE11: 15000 | BF11: 15000 | BG11: 15000 | BH11: 15000 | BI11: 15000 | BJ11: 15000
B12: TOTAL OPEX | C12: =SUM(C9:C11) | D12: =SUM(D9:D11) | E12: =SUM(E9:E11) | F12: =SUM(F9:F11) | G12: =SUM(G9:G11) | H12: =SUM(H9:H11) | I12: =SUM(I9:I11) | J12: =SUM(J9:J11) | ... BJ12: =SUM(BJ9:BJ11)
B13: EBITDA | C13: =C7-C12 | D13: =D7-D12 | E13: =E7-E12 | F13: =F7-F12 | G13: =G7-G12 | H13: =H7-H12 | I13: =I7-I12 | J13: =J7-J12 | ... BJ13: =BJ7-BJ12
B14: Taxes (21%) | C14: =MAX(0, C13*0.21) | D14: =MAX(0, D13*0.21) | E14: =MAX(0, E13*0.21) | F14: =MAX(0, F13*0.21) | G14: =MAX(0, G13*0.21) | H14: =MAX(0, H13*0.21) | I14: =MAX(0, I13*0.21) | J14: =MAX(0, J13*0.21) | ... BJ14: =MAX(0, BJ13*0.21)
B15: NET INCOME | C15: =C13-C14 | D15: =D13-D14 | E15: =E13-E14 | F15: =F13-F14 | G15: =G13-G14 | H15: =H13-H14 | I15: =I13-I14 | J15: =J13-J14 | ... BJ15: =BJ13-BJ14

Sheet Dashboard
B2: EXECUTIVE KPI DASHBOARD
B5: Ending MRR | C5: ='Revenue_Build'!C15
B6: Annual Recurring Revenue (ARR) | C6: ='Revenue_Build'!C15*12
B7: Gross Margin % | C7: ='Financials'!C7/'Financials'!C5
B8: Rule of 40 (Growth + Margin) | C8: =(('Revenue_Build'!D15/'Revenue_Build'!C15)-1) + ('Financials'!C13/'Financials'!C5)
B9: Implied Valuation (10x ARR) | C9: ='Dashboard'!C6*10

Sheet SNA_Outputs
B2: SENSITIVITY ANALYSIS: VALUATION ($M)
B5: Churn \ Growth | C5: 0.03 | D5: 0.04 | E5: 0.05 | F5: 0.06 | G5: 0.07
B6: 0.01 | C6: =(Dashboard!$C$6 * (1 + C5 - $B6)^12 * 10) / 1000000 | D6: =(Dashboard!$C$6 * (1 + D5 - $B6)^12 * 10) / 1000000 | E6: =(Dashboard!$C$6 * (1 + E5 - $B6)^12 * 10) / 1000000 | F6: =(Dashboard!$C$6 * (1 + F5 - $B6)^12 * 10) / 1000000 | G6: =(Dashboard!$C$6 * (1 + G5 - $B6)^12 * 10) / 1000000
B7: 0.015 | C7: =(Dashboard!$C$6 * (1 + C5 - $B7)^12 * 10) / 1000000 | D7: =(Dashboard!$C$6 * (1 + D5 - $B7)^12 * 10) / 1000000 | E7: =(Dashboard!$C$6 * (1 + E5 - $B7)^12 * 10) / 1000000 | F7: =(Dashboard!$C$6 * (1 + F5 - $B7)^12 * 10) / 1000000 | G7: =(Dashboard!$C$6 * (1 + G5 - $B7)^12 * 10) / 1000000
B8: 0.02 | C8: =(Dashboard!$C$6 * (1 + C5 - $B8)^12 * 10) / 1000000 | D8: =(Dashboard!$C$6 * (1 + D5 - $B8)^12 * 10) / 1000000 | E8: =(Dashboard!$C$6 * (1 + E5 - $B8)^12 * 10) / 1000000 | F8: =(Dashboard!$C$6 * (1 + F5 - $B8)^12 * 10) / 1000000 | G8: =(Dashboard!$C$6 * (1 + G5 - $B8)^12 * 10) / 1000000
B9: 0.025 | C9: =(Dashboard!$C$6 * (1 + C5 - $B9)^12 * 10) / 1000000 | D9: =(Dashboard!$C$6 * (1 + D5 - $B9)^12 * 10) / 1000000 | E9: =(Dashboard!$C$6 * (1 + E5 - $B9)^12 * 10) / 1000000 | F9: =(Dashboard!$C$6 * (1 + F5 - $B9)^12 * 10) / 1000000 | G9: =(Dashboard!$C$6 * (1 + G5 - $B9)^12 * 10) / 1000000
B10: 0.03 | C10: =(Dashboard!$C$6 * (1 + C5 - $B10)^12 * 10) / 1000000 | D10: =(Dashboard!$C$6 * (1 + D5 - $B10)^12 * 10) / 1000000 | E10: =(Dashboard!$C$6 * (1 + E5 - $B10)^12 * 10) / 1000000 | F10: =(Dashboard!$C$6 * (1 + F5 - $B10)^12 * 10) / 1000000 | G10: =(Dashboard!$C$6 * (1 + G5 - $B10)^12 * 10) / 1000000
